sample_aditya_pingle_1/__init__.py
sample_aditya_pingle_1-1.0.5.dist-info/DESCRIPTION.rst
sample_aditya_pingle_1-1.0.5.dist-info/METADATA
sample_aditya_pingle_1-1.0.5.dist-info/RECORD
sample_aditya_pingle_1-1.0.5.dist-info/WHEEL
sample_aditya_pingle_1-1.0.5.dist-info/entry_points.txt
sample_aditya_pingle_1-1.0.5.dist-info/metadata.json
sample_aditya_pingle_1-1.0.5.dist-info/top_level.txt
