Metadata-Version: 2.0
Name: sample-aditya-pingle-1
Version: 1.0.5
Summary: Sample project for aditya's pip experiment.
Home-page: https://github.com/adiping1
Author: Aditya Pingle
Author-email: adiping1@umbc.edu
License: MIT
Project-URL: Funding, https://github.com/adiping1/funds
Project-URL: Bug Reports, https://github.com/adiping1/bugs
Project-URL: Say Thanks!, https://github.com/adiping1/thanks
Project-URL: Source, https://github.com/adiping1/src
Keywords: sample aditya piper
Platform: UNKNOWN
Classifier: Development Status :: 3 - Alpha
Classifier: Intended Audience :: Developers
Classifier: Topic :: Software Development :: Build Tools
Classifier: License :: OSI Approved :: MIT License
Classifier: Programming Language :: Python :: 2.7
Requires-Dist: twine
